{
	"credit": "Made with Blockbench",
	"textures": {
		"0": "dawnoftimebuilder:block/cypress_leaves",
		"1": "block/spruce_log",
		"particle": "dawnoftimebuilder:block/cypress_leaves"
	},
	"elements": [
		{
			"from": [6, 10, 6],
			"to": [10, 16, 10],
			"faces": {
				"north": {"uv": [6, 0, 10, 6], "texture": "#0"},
				"east": {"uv": [6, 0, 10, 6], "texture": "#0"},
				"south": {"uv": [6, 0, 10, 6], "texture": "#0"},
				"west": {"uv": [6, 0, 10, 6], "texture": "#0"},
				"up": {"uv": [6, 6, 10, 10], "texture": "#0"},
				"down": {"uv": [6, 6, 10, 10], "texture": "#0"}
			}
		},
		{
			"from": [7, 0, 7],
			"to": [9, 4, 9],
			"faces": {
				"north": {"uv": [7, 0, 9, 4], "texture": "#1"},
				"east": {"uv": [7, 0, 9, 4], "texture": "#1"},
				"south": {"uv": [7, 0, 9, 4], "texture": "#1"},
				"west": {"uv": [7, 0, 9, 4], "texture": "#1"},
				"up": {"uv": [7, 7, 9, 9], "texture": "#1"},
				"down": {"uv": [7, 7, 9, 9], "texture": "#1"}
			}
		},
		{
			"from": [5, 4, 5],
			"to": [11, 10, 11],
			"faces": {
				"north": {"uv": [5, 0, 11, 6], "texture": "#0"},
				"east": {"uv": [5, 0, 11, 6], "texture": "#0"},
				"south": {"uv": [5, 0, 11, 6], "texture": "#0"},
				"west": {"uv": [5, 0, 11, 6], "texture": "#0"},
				"up": {"uv": [5, 5, 11, 11], "texture": "#0"},
				"down": {"uv": [5, 5, 11, 11], "texture": "#0"}
			}
		}
	],
	"display": {
		"thirdperson_righthand": {
			"rotation": [75, 45, 0],
			"translation": [0, 1, 0],
			"scale": [0.375, 0.375, 0.375]
		},
		"thirdperson_lefthand": {
			"rotation": [75, 45, 0],
			"translation": [0, 1, 0],
			"scale": [0.375, 0.375, 0.375]
		},
		"firstperson_righthand": {
			"rotation": [0, 45, 0],
			"scale": [0.4, 0.4, 0.4]
		},
		"firstperson_lefthand": {
			"rotation": [0, 45, 0],
			"scale": [0.4, 0.4, 0.4]
		},
		"ground": {
			"scale": [0.25, 0.25, 0.25]
		},
		"gui": {
			"rotation": [30, 225, 0],
			"scale": [0.9, 0.9, 0.9]
		},
		"head": {
			"rotation": [-40, 0, 0],
			"translation": [0, 11, -10]
		}
	}
}