{
    "variants": {
        "axis=axis_x,open=false,powered=false,vertical_connection=above": { "model": "dawnoftimebuilder:french/iron_portcullis_spike"},
        "axis=axis_x,open=false,powered=true,vertical_connection=above": { "model": "dawnoftimebuilder:french/iron_portcullis_spike"},
        "axis=axis_x,open=false,powered=false,vertical_connection=both": { "model": "dawnoftimebuilder:french/iron_portcullis_middle"},
        "axis=axis_x,open=false,powered=true,vertical_connection=both": { "model": "dawnoftimebuilder:french/iron_portcullis_middle"},
        "axis=axis_x,open=false,powered=false,vertical_connection=under": { "model": "dawnoftimebuilder:french/iron_portcullis_middle"},
        "axis=axis_x,open=false,powered=true,vertical_connection=under": { "model": "dawnoftimebuilder:french/iron_portcullis_middle"},
        "axis=axis_x,open=false,powered=false,vertical_connection=none": { "model": "dawnoftimebuilder:french/iron_portcullis_middle"},
        "axis=axis_x,open=false,powered=true,vertical_connection=none": { "model": "dawnoftimebuilder:french/iron_portcullis_middle"},
        "axis=axis_x,open=true,powered=false,vertical_connection=above": { "model": "block"},
        "axis=axis_x,open=true,powered=true,vertical_connection=above": { "model": "block"},
        "axis=axis_x,open=true,powered=false,vertical_connection=both": { "model": "block"},
        "axis=axis_x,open=true,powered=true,vertical_connection=both": { "model": "block"},
        "axis=axis_x,open=true,powered=false,vertical_connection=under": { "model": "dawnoftimebuilder:french/iron_portcullis_spike"},
        "axis=axis_x,open=true,powered=true,vertical_connection=under": { "model": "dawnoftimebuilder:french/iron_portcullis_spike"},
        "axis=axis_x,open=true,powered=false,vertical_connection=none": { "model": "dawnoftimebuilder:french/iron_portcullis_middle"},
        "axis=axis_x,open=true,powered=true,vertical_connection=none": { "model": "dawnoftimebuilder:french/iron_portcullis_middle"},
        "axis=axis_z,open=false,powered=false,vertical_connection=above": { "model": "dawnoftimebuilder:french/iron_portcullis_spike", "y" : 90},
        "axis=axis_z,open=false,powered=true,vertical_connection=above": { "model": "dawnoftimebuilder:french/iron_portcullis_spike", "y" : 90},
        "axis=axis_z,open=false,powered=false,vertical_connection=both": { "model": "dawnoftimebuilder:french/iron_portcullis_middle", "y" : 90},
        "axis=axis_z,open=false,powered=true,vertical_connection=both": { "model": "dawnoftimebuilder:french/iron_portcullis_middle", "y" : 90},
        "axis=axis_z,open=false,powered=false,vertical_connection=under": { "model": "dawnoftimebuilder:french/iron_portcullis_middle", "y" : 90},
        "axis=axis_z,open=false,powered=true,vertical_connection=under": { "model": "dawnoftimebuilder:french/iron_portcullis_middle", "y" : 90},
        "axis=axis_z,open=false,powered=false,vertical_connection=none": { "model": "dawnoftimebuilder:french/iron_portcullis_middle", "y" : 90},
        "axis=axis_z,open=false,powered=true,vertical_connection=none": { "model": "dawnoftimebuilder:french/iron_portcullis_middle", "y" : 90},
        "axis=axis_z,open=true,powered=false,vertical_connection=above": { "model": "block"},
        "axis=axis_z,open=true,powered=true,vertical_connection=above": { "model": "block"},
        "axis=axis_z,open=true,powered=false,vertical_connection=both": { "model": "block"},
        "axis=axis_z,open=true,powered=true,vertical_connection=both": { "model": "block"},
        "axis=axis_z,open=true,powered=false,vertical_connection=under": { "model": "dawnoftimebuilder:french/iron_portcullis_spike", "y" : 90},
        "axis=axis_z,open=true,powered=true,vertical_connection=under": { "model": "dawnoftimebuilder:french/iron_portcullis_spike", "y" : 90},
        "axis=axis_z,open=true,powered=false,vertical_connection=none": { "model": "dawnoftimebuilder:french/iron_portcullis_middle", "y" : 90},
        "axis=axis_z,open=true,powered=true,vertical_connection=none": { "model": "dawnoftimebuilder:french/iron_portcullis_middle", "y" : 90}
    }
}